MANIFEST.in
requirements.txt
setup.py
Shift.egg-info/PKG-INFO
Shift.egg-info/SOURCES.txt
Shift.egg-info/dependency_links.txt
Shift.egg-info/not-zip-safe
Shift.egg-info/top_level.txt
shift/__init__.py
shift/base.py
shift/engines/__init__.py
shift/engines/bare.py
shift/engines/chameleon.py
shift/engines/cheetah.py
shift/engines/coffeescript.py
shift/engines/creole.py
shift/engines/django.py
shift/engines/genshi.py
shift/engines/jinja2.py
shift/engines/lessc.py
shift/engines/mako.py
shift/engines/markdown.py
shift/engines/markdown_misaka.py
shift/engines/mustache.py
shift/engines/restructuredtext.py
shift/engines/scss.py
shift/engines/textile.py
shift/tests/__init__.py
shift/tests/__main__.py
shift/tests/helpers.py
shift/tests/test_engines.py
shift/tests/test_engines.pyc
shift/tests/test_jinja2.py
shift/tests/test_jinja2.pyc
shift/tests/test_searchpaths.py
shift/tests/test_searchpaths.pyc
shift/tests/__pycache__/test_engines.cpython-32.pyc
shift/tests/__pycache__/test_searchpaths.cpython-32.pyc
shift/tests/templates/test_chameleon.chameleon
shift/tests/templates/test_chameleon.chameleon.out
shift/tests/templates/test_cheetah.cheetah
shift/tests/templates/test_cheetah.cheetah.out
shift/tests/templates/test_creole.creole
shift/tests/templates/test_creole.creole.out
shift/tests/templates/test_django_basic.django
shift/tests/templates/test_django_basic.django.out
shift/tests/templates/test_genshi.markup.genshi
shift/tests/templates/test_genshi.markup.genshi.out
shift/tests/templates/test_genshi.text.genshi
shift/tests/templates/test_genshi.text.genshi.out
shift/tests/templates/test_jinja2_base.j2
shift/tests/templates/test_jinja2_basic.j2
shift/tests/templates/test_jinja2_basic.j2.out
shift/tests/templates/test_jinja2_child.j2
shift/tests/templates/test_jinja2_inheritance.out
shift/tests/templates/test_lesscss.less
shift/tests/templates/test_lesscss.less.out
shift/tests/templates/test_mako_basic.mako
shift/tests/templates/test_mako_basic.mako.out
shift/tests/templates/test_markdown.md
shift/tests/templates/test_markdown.md.out
shift/tests/templates/test_pystache.mustache
